README.md
cozmo-repl
setup.py
cozmo_repl/__init__.py
cozmo_repl/cozmo_main.py
cozmo_repl/cozmo_prompt.py
cozmo_repl/cozmo_repl.py
cozmo_repl.egg-info/PKG-INFO
cozmo_repl.egg-info/SOURCES.txt
cozmo_repl.egg-info/dependency_links.txt
cozmo_repl.egg-info/requires.txt
cozmo_repl.egg-info/top_level.txt