Metadata-Version: 1.0
Name: cozmo-repl
Version: 0.3.0
Summary: IPython REPL for Cozmo
Home-page: UNKNOWN
Author: Adrien Becchis
Author-email: adriean.khisbe@live.fr
License: Apache2
Platform: UNKNOWN
